pun/__init__.py
pun/_version.py
pun/py.typed
pun-0.1.0.dist-info/METADATA
pun-0.1.0.dist-info/WHEEL
pun-0.1.0.dist-info/licenses/LICENSE
pun-0.1.0.dist-info/RECORD
