Metadata-Version: 2.4
Name: pun
Version: 0.1.0
Summary: This is a pun
Project-URL: changelog, https://github.com/hasansezertasan/pun/blob/main/CHANGELOG.md
Project-URL: documentation, https://github.com/hasansezertasan/pun#readme
Project-URL: homepage, https://github.com/hasansezertasan/pun
Project-URL: issues, https://github.com/hasansezertasan/pun/issues
Project-URL: releasenotes, https://github.com/hasansezertasan/pun/releases
Project-URL: source, https://github.com/hasansezertasan/pun.git
Author-email: Hasan Sezer Taşan <hasansezertasan@gmail.com>
Maintainer-email: Hasan Sezer Taşan <hasansezertasan@gmail.com>
License-Expression: MIT
License-File: LICENSE
Keywords: pun
Classifier: Development Status :: 1 - Planning
Classifier: Typing :: Typed
Requires-Python: >=3.10
